{"@class":"Animation","id":{"uuid":"12822431-5A35-456F-8CB8-868E4B8B0924"},"tracks":[{"@class":"Vector3BehaviorTrack","clips":[{"@class":"Vector3BehaviorClip","beginTime":0,"duration":5166,"script":"Vector3ValueBehaviorClipScript","behavior":{"@class":"Vector3PlainBehavior","times":[0,5166],"values":[2.2351741790771486e-8,0.07872273027896881,-3.725290298461914e-9,2.2351741790771486e-8,0.07872273027896881,-3.725290298461914e-9]}}],"script":"Vector3BehaviorTrackScript","accessor":"PositionBlendAccessor"},{"@class":"QuaternionBehaviorTrack","clips":[{"@class":"QuaternionBehaviorClip","beginTime":0,"duration":5166,"script":"QuaternionValueBehaviorClipScript","behavior":{"@class":"QuaternionPlainBehavior","times":[0,5166],"values":[0.17103488743305207,0.035886239260435107,0.02634790912270546,0.9842586517333984,0.17103488743305207,0.035886239260435107,0.02634790912270546,0.9842586517333984]}}],"script":"QuaternionBehaviorTrackScript","accessor":"RotationQBlendAccessor"},{"@class":"Vector3BehaviorTrack","clips":[{"@class":"Vector3BehaviorClip","beginTime":0,"duration":5166,"script":"Vector3ValueBehaviorClipScript","behavior":{"@class":"Vector3PlainBehavior","times":[0,5166],"values":[1.0,1.0,0.9999998807907105,1.0,1.0,0.9999998807907105]}}],"script":"Vector3BehaviorTrackScript","accessor":"ScaleBlendAccessor"}]}