{"@class":"TimeLineScript","id":{"uuid":"D9AA9E05-BAA3-43FD-8331-01BEAB20E7B6"},"name":"Animation","enableOnAwake":false,"loop":true,"jumpToFirstFrameAtEnd":false,"speed":1.0,"weight":1.0,"loopStartTime":0,"loopDuration":0,"is_imported":false,"type":"user","scripts":{"@class":"StdListRuntimeScript","list":[{"@class":"AnimationScript","id":{"uuid":"F5C7B4EF-7BAB-42E3-8528-8FF8DB482783"},"name":"OCean_plane","enableOnAwake":false,"OwnerLink":{"@class":"BindingLink","targetId":{"uuid":"DEFE4139-46F7-41BC-8473-410FE1E776E4"},"targetRelativeAddress":{"@class":"NodeRelativeAddressBase","index":0,"name":"Ocean","subaddress":{"@class":"NodeRelativeAddressBase","index":0,"name":"OCean_plane"}}},"animation":{"uuid":"18D5F8B2-F339-4A67-9429-DC9886A1E10A"},"AnimationType":"object3D","is_imported":false,"isEnabled":true}]},"triggers":[{"@class":"StartTrigger","id":{"uuid":"18F9B71D-D61C-430A-86FC-58F0A7FB19F9"},"ownerScriptId":{"uuid":"D9AA9E05-BAA3-43FD-8331-01BEAB20E7B6"},"logicOperation":0,"resultType":0,"isInverted":false}]}